llm_image_classifier/__init__.py
llm_image_classifier/main.py
llm_image_classifier/llm/__init__.py
llm_image_classifier/llm/llm_with_groq_and_chromadb.py
llm_image_classifier/middleware/__init__.py
llm_image_classifier/middleware/utils_llm.py
llm_image_classifier/middleware/utils_log.py
llm_image_classifier/middleware/utils_os.py
llm_image_classifier/models/__init__.py
llm_image_classifier/models/abstract_model_class.py
llm_image_classifier/models/manager_model.py
llm_image_classifier/models/models.py
llm_image_classifier/models/save_files_class.py
llm_image_classifier/models/available_models/__init__.py
llm_image_classifier/models/available_models/inceptionv3.py
llm_image_classifier/models/available_models/mobile_net.py
llm_image_classifier/models/available_models/resnet50.py
llm_image_classifier/models/available_models/sequential_keras.py
llm_image_classifier/models/available_models/vgg19.py
llm_image_classifier/models/available_models/xception.py
llm_image_classifier/routes/__init__.py
llm_image_classifier/routes/llm_routes.py
llm_image_classifier/routes/log_routes.py
llm_image_classifier/routes/screen_routes.py
llm_image_classifier/routes/training_model_routes.py
llm_image_classifier/routes/utils_routes.py
llm_image_classifier/ui/statics/images/home_image.png
llm_image_classifier/ui/statics/images/source_code_icon.png
llm_image_classifier/ui/statics/images/upload_file_icon.png
llm_image_classifier/ui/statics/scripts/chat.js
llm_image_classifier/ui/statics/scripts/dataset.js
llm_image_classifier/ui/statics/scripts/drag_drop_input_file.js
llm_image_classifier/ui/statics/scripts/form.js
llm_image_classifier/ui/statics/scripts/logs.js
llm_image_classifier/ui/statics/scripts/test_model.js
llm_image_classifier/ui/statics/styles/chat.css
llm_image_classifier/ui/statics/styles/dataset.css
llm_image_classifier/ui/statics/styles/drag_drop_input_file.css
llm_image_classifier/ui/statics/styles/form.css
llm_image_classifier/ui/statics/styles/home.css
llm_image_classifier-1.0.2.dist-info/LICENSE
llm_image_classifier-1.0.2.dist-info/METADATA
llm_image_classifier-1.0.2.dist-info/WHEEL
llm_image_classifier-1.0.2.dist-info/entry_points.txt
llm_image_classifier-1.0.2.dist-info/top_level.txt
llm_image_classifier-1.0.2.dist-info/RECORD
