Metadata-Version: 2.1
Name: llm_image_classifier
Version: 1.0.2
Summary: Ferramenta de suporte para treinamentoe análise de modelo de classificação de imagem com assistente virtual integrado
Author: Gabriel Batista, Fábio Santos
Author-email: gabrielpjl27@gmail.com, fssilva@uea.edu.br
Maintainer: Gabriel Batista, Fábio Santos
Maintainer-email: gabrielpjl27@gmail.com, fssilva@uea.edu.br
Classifier: Programming Language :: Python :: 3
Classifier: Framework :: FastAPI
Classifier: License :: OSI Approved :: MIT License
Classifier: Operating System :: OS Independent
Requires-Python: >=3.10
License-File: LICENSE
Requires-Dist: fastapi
Requires-Dist: uvicorn
Requires-Dist: jinja2
Requires-Dist: tf_keras
Requires-Dist: scikit-learn
Requires-Dist: matplotlib
Requires-Dist: chromadb
Requires-Dist: sentence-transformers
Requires-Dist: groq
Requires-Dist: python-multipart
